{
  "Grade4": {
    "FirstTerm": {
      "Science": {
        "units": [
          {
            "unit": "unit1",
            "title": "الجهاز الهضمي",
            "lessons": [
              {
                "id": 1,
                "title": "الجهاز الهضمي",
                "description": "<p>يبدي كل كائن حي عددا من التكيفات المختلفة، ولكن كيف تعمل هذه التكيفات المختلفة معا؟ يُطلق على أجزاء الجسم التي تعمل معا اسم الأجهزة. يتكون الجهاز من أعضاء كثيرة تعمل معا لتحافظ على بقاء الكائن الحي. كيف تتكيف أجهزة الجسم لتلبي الاحتياجات الخاصة به؟ دعونا نتناول بالدراسة مثالين: الجهاز الهضمي والجهاز التنفسي. ربما لم يطرأ على ذهنك سابقا كيف نتنفس أو كيف يهضم الجسم الطعام للحصول على الطاقة. هل كل الحيوانات تأكل وتتنفس مثل الإنسان من المهم فهم الفرق بين أجهزة الجسم في الإنسان والحيوانات الأخرى. اقرأ النص التالي ، ثم أجب عن الأسئلة.</p><p>الجهاز الهضمي للإنسان</p><p>هل سألت نفسك ماذا يفعل جسمك بالطعام الذي تأكله؟ أو لماذا نحتاج إلى الطعام؟</p><p>يحصل جسمك على العناصر الغذائية من الطعام. ويحصل أيضا على الطاقة من بعض هذه العناصر. فأنت تحتاج إلى هذه الطاقة لتتمكن من المشي، أو التحدث أو النوم. كما يحتاج جسمك إلى الطاقة ليتمكن من أداء وظائفه الداخلية. يحتاج جسمك إلى الطاقة ليتمكن قلبك من النبض، ورئتيك من التنفس وعقلك من التفكير.</p><p>يستعين جسمك بالجهاز الهضمي ليمده بالعناصر الغذائية الموجودة في الطعام، يتكون الجهاز الهضمي من أعضاء مختلفة تعمل هذه الأعضاء معا لتفتيت الطعام إلى أجزاء صغيرة حتى يتسنى للجسم الاستفادة منها.</p><p>تبدأ عملية الهضم من الفم. عندما تأخذ قضمة من الطعام، يبدأ اللعاب بترطيبه وتفتيته، تعمل أسنانك ولسانك معا لمزج الطعام وطحنه حتى يصبح طريا ولينا.</p><p>عندما تبدأ بالبلع، يقوم الحلق بدفع الطعام داخل أنبوب يسمى المريء، يحتوي هذا الأنبوب على عضلات تحرك الطعام إلى المعدة، تقوم معدتك بخلط الطعام بحمض المعدة والعصارات الهضمية، والإنزيمات، ويظل الطعام داخل المعدة لعدة ساعات إلى أن يتحول إلى سائل، ثم تقوم عضلات المعدة بتحريك الطعام ونقله إلى أنبوب ملتف وطويل، هذا الأنبوب يسمى الأمعاء الدقيقة، والتي إذا تم فردها طوليا ستجد أن طولها يزيد عن ستة أمتار، يستمر هضم الطعام داخل هذه الأمعاء الدقيقة، وتتدفق عصارات الكبد والبنكرياس إلى الأمعاء الدقيقة ما يساعد على هضم الطعام وتحوله إلى عناصر غذائية.</p><p>يتم امتصاص العناصر الغذائية عبر جدران الأمعاء الدقيقة. وتنفذ هذه العناصر إلى داخل شعيرات دموية دقيقة، يحمل الدم هذه العناصر الغذائية ويوزعها على كل أجزاء الجسم.</p><p>هناك بعضا من الطعام الذي لم يتم هضمه لن يستفيد منه جسمك. فيتدفق هذا الطعام داخل الأمعاء الغليظة. تمتص الأمعاء الغليظة السوائل من الطعام غير المهضوم، فيصبح بذلك من الفضلات الصلبة. تنتقل هذه الفضلات خارج الجسم عن طريق فتحة الشرج.</p><p>يحتاج جسمك في اليوم الواحد لمقدار كبير من الطاقة حيث ينبض قلبك ما يقرب من ۱۰۰۰۰۰۰ نبضة يوميا، كما أنك تتنفس أكثر من ۲۰۰٠٠ مرة يوميا وتخطو آلاف الخطوات يوميا. جهازك الهضمي يساعد جسمك على الحصول على العناصر الغذائية والطاقة اللازمة.</p>",
                "image": "/images/digestive_system.jpg",
                "model": "/models/realistic digestive system.glb",
                "questions": [
                  {
                    "question": "ما وظيفة الجهاز الهضمي في جسم الإنسان؟",
                    "choices": [
                      "تنظيم التنفس",
                      "نقل الدم",
                      "تفتيت الطعام وامتصاص العناصر الغذائية",
                      "تنظيم ضربات القلب"
                    ],
                    "answer": "تفتيت الطعام وامتصاص العناصر الغذائية"
                  },
                  {
                    "question": "أين تبدأ عملية الهضم؟",
                    "choices": [
                      "في الأمعاء الدقيقة",
                      "في المعدة",
                      "في الفم",
                      "في الكبد"
                    ],
                    "answer": "في الفم"
                  },
                  {
                    "question": "ما العضو الذي يقوم بخلط الطعام بالعصارات والإنزيمات؟",
                    "choices": ["الكبد", "المعدة", "الأمعاء الدقيقة", "المريء"],
                    "answer": "المعدة"
                  },
                  {
                    "question": "ما طول الأمعاء الدقيقة تقريبا إذا تم فردها؟",
                    "choices": [
                      "ثلاثة أمتار",
                      "أربعة أمتار",
                      "أكثر من ستة أمتار",
                      "أقل من مترين"
                    ],
                    "answer": "أكثر من ستة أمتار"
                  },
                  {
                    "question": "ما الذي يحدث للطعام غير المهضوم؟",
                    "choices": [
                      "يمتصه الكبد",
                      "يتحول إلى سكر في الدم",
                      "يُطرح كفضلات عبر فتحة الشرج",
                      "يُخزن في المعدة"
                    ],
                    "answer": "يُطرح كفضلات عبر فتحة الشرج"
                  }
                ]
              },
              {
                "id": 2,
                "title": "الدرس الثاني",
                "description": "<p>محتوى الدرس 2</p>",
                "image": "/images/digestive_system_lesson2.jpg",
                "model": "/models/digestive_system_model2.glb"
              }
            ]
          },
          {
            "unit": "unit2",
            "title": "الجهاز التنفسي",
            "lessons": [
              {
                "id": 1,
                "title": "الجهاز التنفسي",
                "description": "<p>محتوى الدرس 2</p>",
                "image": "/images/respiratory_system.jpg",
                "model": "/models/respiratory_system_model.glb"
              }
            ]
          }
        ]
      },
      "Math": {
        "units": [
          {
            "unit": "unit1",
            "title": "الجمع",
            "lessons": [
              {
                "id": 1,
                "title": "الدرس الأول",
                "description": "<p>محتوى الدرس 1</p>",
                "image": "/images/fraction_lesson1.jpg",
                "model": "/models/fraction_model1.glb"
              }
            ]
          }
        ]
      }
    },
    "SecondTerm": {
      "Science": {
        "units": [
          {
            "unit": "unit1",
            "title": "الطاقة",
            "lessons": [
              {
                "id": 1,
                "title": "الطاقة",
                "description": "<p>محتوى الدرس 1</p>",
                "image": "/images/energy.jpg",
                "model": "/models/energy_model.glb"
              }
            ]
          }
        ]
      },
      "Math": {
        "units": [
          {
            "unit": "unit1",
            "title": "الطرح",
            "lessons": [
              {
                "id": 1,
                "title": "الدرس الأول",
                "description": "<p>محتوى الدرس 1</p>",
                "image": "/images/subtraction_lesson1.jpg",
                "model": "/models/subtraction_model1.glb"
              }
            ]
          }
        ]
      }
    }
  },
  "Grade5": {
    "FirstTerm": {
      "Science": {
        "units": [
          {
            "unit": "unit1",
            "title": "الجهاز العصبي",
            "lessons": [
              {
                "id": 1,
                "title": "الجهاز العصبي",
                "description": "<p>محتوى الدرس 1</p>",
                "image": "/images/nervous_system.jpg",
                "model": "/models/nervous_system_model.glb"
              }
            ]
          }
        ]
      },
      "Math": {
        "units": [
          {
            "unit": "unit1",
            "title": "الكسور العشرية",
            "lessons": [
              {
                "id": 1,
                "title": "الدرس الأول",
                "description": "<p>محتوى الدرس 1</p>",
                "image": "/images/decimal_fractions_lesson1.jpg",
                "model": "/models/decimal_fraction_model1.glb"
              }
            ]
          }
        ]
      }
    }
  }
}
